tellonym_api/__init__.py
tellonym-1.0.0.dist-info/LICENSE
tellonym-1.0.0.dist-info/METADATA
tellonym-1.0.0.dist-info/WHEEL
tellonym-1.0.0.dist-info/top_level.txt
tellonym-1.0.0.dist-info/RECORD
