Metadata-Version: 2.1
Name: tellonym
Version: 1.0.0
Summary: A Python tellonym api
Home-page: https://github.com/PatchByte/pyhton-tellonym-api
Author: PatchByte
Author-email: sorrynoemail@email.com
License: UNKNOWN
Platform: UNKNOWN
Classifier: Programming Language :: Python :: 3
Requires-Python: >=3.6
